django_admin_pro/__init__.py
django_admin_pro/admin.py
django_admin_pro/apps.py
django_admin_pro/context_processors.py
django_admin_pro/field_item.py
django_admin_pro/filters.py
django_admin_pro/middleware.py
django_admin_pro/resource.py
django_admin_pro/resource_manager.py
django_admin_pro/urls.py
django_admin_pro/views.py
django_admin_pro/fields/EmailField.py
django_admin_pro/fields/Field.py
django_admin_pro/fields/IDField.py
django_admin_pro/fields/PasswordField.py
django_admin_pro/fields/TextField.py
django_admin_pro/fields/TextareaField.py
django_admin_pro/fields/__init__.py
django_admin_pro/templates/app.html
django_admin_pro/templates/dashboard.html
django_admin_pro/templates/detail.html
django_admin_pro/templates/footer.html
django_admin_pro/templates/index.html
django_admin_pro/templates/layout.html
django_admin_pro/templates/new.html
django_admin_pro/templates/sidebar.html
django_admin_pro/templates/fields/input.html
django_admin_pro/templates/fields/select.html
django_admin_pro/templates/fields/textarea.html
django_admin_pro-0.1.3.dist-info/METADATA
django_admin_pro-0.1.3.dist-info/WHEEL
django_admin_pro-0.1.3.dist-info/top_level.txt
django_admin_pro-0.1.3.dist-info/RECORD
