Metadata-Version: 2.1
Name: django-admin-pro
Version: 0.1.3
Summary: Django Admin Pro
Author-email: Krunal Dodiya <krunal@example.com>
License: MIT
Requires-Python: >=3.10
